./.gitignore
./PKG-INFO
./README.md
./cli.py
./cli_simple.py
./cli_utils.py
./mcp_server.py
./pyproject.toml
./src/__init__.py
./src/config.py
./src/config.yaml
./src/main.py
./src/run.py
./src/baml_client/__init__.py
./src/baml_client/async_client.py
./src/baml_client/config.py
./src/baml_client/globals.py
./src/baml_client/inlinedbaml.py
./src/baml_client/parser.py
./src/baml_client/runtime.py
./src/baml_client/stream_types.py
./src/baml_client/sync_client.py
./src/baml_client/tracing.py
./src/baml_client/type_builder.py
./src/baml_client/type_map.py
./src/baml_client/types.py
./src/cache/__init__.py
./src/executor/__init__.py
./src/executor/assertion_api/__init__.py
./src/executor/assertion_api/element.py
./src/executor/assertion_api/pydantic_schema.py
./src/executor/assertion_api/session.py
./src/executor/assertion_api/state.py
./src/executor/assertion_api/type_utils.py
./src/executor/automators/README.md
./src/executor/automators/custom.py
./src/executor/automators/pyautogui.py
./src/executor/automators/uitars.py
./src/executor/page_reidentification/abstract.py
./src/executor/page_reidentification/accessibility.py
./src/executor/page_reidentification/distance.py
./src/parser/__init__.py
./src/utils/video.py
ieee_gui-0.0.27.dist-info/METADATA
ieee_gui-0.0.27.dist-info/WHEEL
ieee_gui-0.0.27.dist-info/entry_points.txt
ieee_gui-0.0.27.dist-info/RECORD
