Metadata-Version: 2.4
Name: ieee-gui
Version: 0.0.27
Summary: Testing
Requires-Python: >=3.12
Requires-Dist: anthropic>=0.61.0
Requires-Dist: baml-py==0.205.0
Requires-Dist: fastmcp>=2.13.2
Requires-Dist: google-genai>=1.29.0
Requires-Dist: matplotlib>=3.10.3
Requires-Dist: moviepy>=2.2.1
Requires-Dist: numba>=0.61.2
Requires-Dist: openai>=1.95.1
Requires-Dist: opencv-python>=4.12.0.88
Requires-Dist: pillow>=11.3.0
Requires-Dist: playwright>=1.53.0
Requires-Dist: pydantic>=2.11.7
Requires-Dist: python-dotenv>=1.1.1
Requires-Dist: python-levenshtein>=0.27.1
Requires-Dist: pyyaml>=6.0.2
Requires-Dist: scikit-image>=0.25.2
Requires-Dist: typer>=0.9.0
Requires-Dist: zss>=1.2.0
